{
  "credentials": [
    {
      "category": "Coding Languages",
      "skills": [
        "HTML",
        "JavaScript",
        "PHP",
        "Python",
        "Ruby",
        "CSS/SASS"
      ]
    },
    {
      "category": "PHP Platforms & Frameworks",
      "skills": [
        "Craft",
        "Drupal",
        "Pattern Lab",
        "Symfony",
        "WordPress"
      ]
    },
    {
      "category": "JavaScript Frameworks & Libraries",
      "skills": [
        "Alpine.js",
        "Gatsby",
        "Next.js",
        "Storybook",
        "Vue.js"
      ]
    },
    {
      "category": "Visualization & Mapping Frameworks/APIs",
      "skills": [
        "Esri",
        "Google Maps/Places",
        "Chart.js",
        "HTML Canvas",
        "Leaflet.js"
      ]
    },
    {
      "category": "JavaScript Build Tools",
      "skills": [
        "Babel",
        "Gulp",
        "Grunt",
        "Webpack",
        "Vite",
        "Yomen"
      ]
    },
    {
      "category": "Package Managers",
      "skills": [
        "Bower",
        "Composer",
        "NPM",
        "Yarn"
      ]
    },
    {
      "category": "Testing & Debugging",
      "skills": [
        "Backstop",
        "Cypress",
        "Xdebug"
      ]
    }
  ]
}
